[null,{"name":"ErrorMessage","temp":"db-error","event-type":"37","_id":"PwJwI","actions":[{"channel":"4","varName":"","message":"","buttons":[],"selectMenus":[],"attachments":[],"embeds":[{"title":"An error occured!","url":"","color":"#FFA17A","timestamp":"false","imageUrl":"","thumbUrl":"","description":"Oops, something went horribly wrong!\nDBM error:\n`${tempVars(\"db-error\")}`\n\nJS error:\n`${tempVars(\"js-error\")}`","fields":[],"author":"","authorUrl":"","authorIcon":"","footerText":"","footerIconUrl":""}],"reply":true,"ephemeral":false,"tts":false,"overwrite":false,"dontSend":false,"editMessage":"0","editMessageVarName":"","storage":"0","varName2":"","name":"Send Message"}],"temp2":"js-error"},{"name":"StartActivity","temp":"","event-type":"48","_id":"OAoEM","actions":[{"status":"0","name":"Set Bot Status"},{"gameName":"our developers","gameLink":"","activityType":"WATCHING","name":"Set Bot Game"}]}]